composition/__init__.py
composition/api.py
composition/cmd.py
composition/composer.py
composition/directory.py
composition/install.py
composition/list_apps.py
composition/logs.py
composition/models.py
composition/storage.py
composition/subapps.py
composition/template_cmd.py
composition/uninstall.py
docker_composition-1.0.5.dist-info/METADATA
docker_composition-1.0.5.dist-info/WHEEL
docker_composition-1.0.5.dist-info/entry_points.txt
docker_composition-1.0.5.dist-info/RECORD
