Metadata-Version: 2.1
Name: docker-composition
Version: 1.0.5
Summary: Docker-compose package manager
Project-URL: Homepage, https://github.com/sam-technesci/composer
Author-email: sam <sam@fake.com>
Requires-Dist: click
Requires-Dist: humanize
Requires-Dist: jinja2
Requires-Dist: petname
Requires-Dist: pyyaml
